{"last_tab":"1","favicon":{"url":"http:\/\/bouwercons.jwsthemeswp.com\/wp-content\/uploads\/2019\/03\/favicon.png","id":"1534","height":"55","width":"48","thumbnail":"http:\/\/bouwercons.jwsthemeswp.com\/wp-content\/uploads\/2019\/03\/favicon.png","title":"favicon","caption":"","alt":"","description":""},"loading":"0","logo_loading":{"url":"http:\/\/bouwercons.jwsthemeswp.com\/wp-content\/uploads\/2019\/03\/favicon.png","id":"1534","height":"55","width":"48","thumbnail":"http:\/\/bouwercons.jwsthemeswp.com\/wp-content\/uploads\/2019\/03\/favicon.png","title":"favicon","caption":"","alt":"","description":""},"header_global":"7","header1_review":"1","select-header1":"10","select-header-mb1":"1406","header2_review":"1","select-header2":"15","select-header-mb2":"1439","header3_review":"1","select-header3":"39","select-header-mb3":"1449","header4_review":"1","select-header4":"531","select-header-mb4":"1462","header5_review":"1","select-header5":"565","select-header-mb5":"1463","header6_review":"1","select-header6":"663","select-header-mb6":"1469","header7_review":"1","select-header7":"799","select-header-mb7":"1484","footer_global":"3","footer1_review":"1","select-footer1":"269","footer2_review":"1","select-footer2":"516","footer3_review":"1","select-footer3":"784","main-color":"#fd8a14","color1":"#575454","color2":"#444444","color3":"#333333","color4":"#999999","projects_layout":"layout1","height_thumbnail":"740px","blogs_layout":"layout1","height_thumbnail_blog":"740px","image_size_blog":"770x460","position_sidebar":"right","bat_related_post":"1","select-page-404":"1203","shop_post_number":"4","shop_columns":"3","opt-typography-body":{"font-family":"Roboto","font-options":"","google":"1","font-weight":"400","font-style":"","subsets":"","text-align":"","font-size":"17px","line-height":"28px","color":"#666666"},"font1":{"font-family":"Poppins","font-options":"","google":"1"},"themecheck_style":"0","redux-backup":"1"}